AUTHORS.rst
CHANGELOG.rst
LICENSE
MANIFEST.in
README.rst
requirements-dev.txt
requirements.txt
setup.py
unicore_gitmodels/__init__.py
unicore_gitmodels/__init__.pyc
unicore_gitmodels/fields.py
unicore_gitmodels/fields.pyc
unicore_gitmodels/models.py
unicore_gitmodels/models.pyc
unicore_gitmodels.egg-info/PKG-INFO
unicore_gitmodels.egg-info/SOURCES.txt
unicore_gitmodels.egg-info/dependency_links.txt
unicore_gitmodels.egg-info/not-zip-safe
unicore_gitmodels.egg-info/requires.txt
unicore_gitmodels.egg-info/top_level.txt
unicore_gitmodels/tests/__init__.py
unicore_gitmodels/tests/__init__.pyc
unicore_gitmodels/tests/test_fields.py
unicore_gitmodels/tests/test_models.py
unicore_gitmodels/tests/test_models.pyc
unicore_gitmodels/tests/__pycache__/test_fields.cpython-27-PYTEST.pyc
unicore_gitmodels/tests/__pycache__/test_models.cpython-27-PYTEST.pyc