Metadata-Version: 1.1
Name: unicore-gitmodels
Version: 1.7.0
Summary: Definition of models used for python-gitmodel
Home-page: http://github.com/praekelt/unicore-gitmodels
Author: Praekelt Foundation
Author-email: dev@praekelt.com
License: BSD
Platform: UNKNOWN
Classifier: Programming Language :: Python
Classifier: License :: OSI Approved :: BSD License
Classifier: Development Status :: 4 - Beta
Classifier: Operating System :: OS Independent
Classifier: Intended Audience :: Developers
Classifier: Topic :: Internet :: WWW/HTTP :: Dynamic Content
